gpucsl/__init__.py
gpucsl/__main__.py
gpucsl/cli/__init__.py
gpucsl/cli/cli.py
gpucsl/cli/cli_io.py
gpucsl/cli/cli_util.py
gpucsl/cli/command_line_parser.py
gpucsl/pc/__init__.py
gpucsl/pc/discover_skeleton_discrete.py
gpucsl/pc/discover_skeleton_gaussian.py
gpucsl/pc/gaussian_device_manager.py
gpucsl/pc/helpers.py
gpucsl/pc/kernel_management.py
gpucsl/pc/pc.py
gpucsl/pc/pc_validations.py
gpucsl/pc/cuda/discrete_ci.cu
gpucsl/pc/cuda/gaussian_ci.cu
gpucsl/pc/cuda/helpers/discrete_helpers.cu
gpucsl/pc/cuda/helpers/gaussian_helpers.cu
gpucsl/pc/cuda/helpers/graph_helpers.cu
gpucsl/pc/cuda/helpers/math_helpers.cu
gpucsl/pc/cuda/helpers/set_helpers.cu
gpucsl/pc/edge_orientation/__init__.py
gpucsl/pc/edge_orientation/edge_orientation.py
gpucsl/pc/edge_orientation/orientation_rules.py
gpucsl/pc/edge_orientation/v_structures.py
tests/__init__.py
tests/asserts.py
tests/conftest.py
tests/equality.py
tests/test_cli.py
tests/test_cuda_discrete_helpers.py
tests/test_cuda_gaussian_helpers.py
tests/test_cuda_graph_helpers.py
tests/test_cuda_set_helpers.py
tests/test_gaussian_device_manager.py
tests/test_gpucsl.py
tests/test_kernel_management.py
tests/test_pc.py
tests/test_skeleton_discrete.py
tests/test_skeleton_gaussian.py
tests/edge_orientation/__init__.py
tests/edge_orientation/test_edge_orientation.py
tests/edge_orientation/test_orientation_rules.py
tests/edge_orientation/test_v_structures.py
tests/fixtures/__init__.py
tests/fixtures/file_readers.py
tests/fixtures/generated_input_data_and_results.py
tests/fixtures/input_data.py
tests/fixtures/input_data_discrete.py
tests/fixtures/test_fixtures.py
gpucsl-0.0.7.dist-info/LICENSE
gpucsl-0.0.7.dist-info/METADATA
gpucsl-0.0.7.dist-info/WHEEL
gpucsl-0.0.7.dist-info/top_level.txt
gpucsl-0.0.7.dist-info/RECORD
