Metadata-Version: 2.1
Name: gpucsl
Version: 0.0.7
Summary: A library for constraint-based causal structure learning on GPUs.
Home-page: https://github.com/hpi-epic/gpucsl
Author: Tom Braun, Petr Tsayun, Dominik Meier, Ben Hurdelhey
Author-email: author@example.com
License: UNKNOWN
Project-URL: Bug Tracker, https://github.com/hpi-epic/gpucsl/issues
Platform: UNKNOWN
Classifier: Programming Language :: Python :: 3
Classifier: Operating System :: OS Independent
Requires-Python: >=3.8
License-File: LICENSE
Requires-Dist: numpy
Requires-Dist: scipy
Requires-Dist: pandas
Requires-Dist: networkx
Requires-Dist: scikit-learn
Requires-Dist: colorama
Provides-Extra: dev
Requires-Dist: pytest ; extra == 'dev'
Requires-Dist: pytest-lazy-fixture ; extra == 'dev'
Requires-Dist: pytest-mock ; extra == 'dev'
Requires-Dist: pytest-timeout ; extra == 'dev'
Requires-Dist: flake8 ; extra == 'dev'
Requires-Dist: black (==22.3.0) ; extra == 'dev'
Requires-Dist: black[jupyter] (==22.3.0) ; extra == 'dev'
Requires-Dist: build ; extra == 'dev'
Requires-Dist: pytest-cov ; extra == 'dev'
Requires-Dist: virtualenv ; extra == 'dev'
Requires-Dist: manm-cs (>=0.1.0) ; extra == 'dev'
Requires-Dist: twine ; extra == 'dev'
Requires-Dist: seaborn ; extra == 'dev'
Requires-Dist: gdown ; extra == 'dev'
